web_compressor/__init__.py
web_compressor/cli/__init__.py
web_compressor/cli/config.py
web_compressor/core.py
web_compressor/handlers/__init__.py
web_compressor/handlers/handler.py
web_compressor/handlers/hasher.py
web_compressor/handlers/minifier.py
web_compressor/handlers/optimizer.py
web_compressor/logger.py
web_compressor/utils.py
web_compressor-0.4.2.dist-info/entry_points.txt
web_compressor-0.4.2.dist-info/LICENSE
web_compressor-0.4.2.dist-info/WHEEL
web_compressor-0.4.2.dist-info/METADATA
web_compressor-0.4.2.dist-info/RECORD
