Metadata-Version: 2.1
Name: web-compressor
Version: 0.4.2
Summary: Supercharges HTML files & web assets
Home-page: https://digitalbuero.eu
License: GPL-3.0-only
Keywords: cache-busting,cachebusting,cli,csp,content-security-policy,fingerprinting,hashing,imageoptim,minification,minifier,minify,optimization,sri,subresource-integrity
Author: Digitalbüro
Author-email: post@digitalbuero.eu
Maintainer: Martin Folkers
Maintainer-email: hello@twobrain.io
Requires-Python: >=3.8,<4.0
Classifier: Development Status :: 4 - Beta
Classifier: Environment :: Console
Classifier: Intended Audience :: Developers
Classifier: License :: OSI Approved :: GNU General Public License v3 (GPLv3)
Classifier: Operating System :: OS Independent
Classifier: Programming Language :: Python :: 3
Classifier: Programming Language :: Python :: 3.8
Classifier: Programming Language :: Python :: 3.9
Classifier: Programming Language :: Python :: 3.10
Classifier: Programming Language :: Python :: 3.10
Classifier: Programming Language :: Python :: 3.8
Classifier: Programming Language :: Python :: 3.9
Classifier: Topic :: Internet :: WWW/HTTP
Classifier: Topic :: Software Development :: Libraries :: Python Modules
Provides-Extra: cli
Provides-Extra: images
Provides-Extra: minify
Requires-Dist: Pillow (>=9,<10); extra == "images"
Requires-Dist: beautifulsoup4 (>=4,<5)
Requires-Dist: click (>=8,<9); extra == "cli"
Requires-Dist: pillow-avif-plugin (>=1.2,<2.0); extra == "images"
Requires-Dist: tdewolff-minify (>=2,<3); extra == "minify"
Requires-Dist: tomli (>=2,<3); (python_version < "3.11") and (extra == "cli")
Requires-Dist: tomli-w (>=1,<2); extra == "cli"
Requires-Dist: xdg (>=5,<6); extra == "cli"
Project-URL: Funding, https://donate.rsf.org
Project-URL: Issue Tracker, https://codeberg.org/digitalbuero/web-compressor/issues
Project-URL: Repository, https://codeberg.org/digitalbuero/web-compressor
